MCPserver.py
rhodecode_mcp_server-1.1.5.dist-info/licenses/LICENSE
rhodecode_mcp_server-1.1.5.dist-info/METADATA
rhodecode_mcp_server-1.1.5.dist-info/WHEEL
rhodecode_mcp_server-1.1.5.dist-info/entry_points.txt
rhodecode_mcp_server-1.1.5.dist-info/top_level.txt
rhodecode_mcp_server-1.1.5.dist-info/RECORD
