Metadata-Version: 2.4
Name: rhodecode-mcp-server
Version: 1.1.5
Summary: MCP Server para interactuar con RhodeCode API - Gestión de repositorios y Pull Requests
Author-email: Bruno Izaguirre <bruno.izaguirre@example.com>
License: MIT
Project-URL: Homepage, https://github.com/BrunoIzaguMart/MCPRhodecoder
Project-URL: Documentation, https://github.com/BrunoIzaguMart/MCPRhodecode/blob/main/README.md
Project-URL: Repository, https://github.com/BrunoIzaguMart/MCPRhodecode
Project-URL: Issues, https://github.com/BrunoIzaguMart/MCPRhodecode/issues
Keywords: mcp,rhodecode,api,git,mercurial,repositories,pull-requests
Classifier: Development Status :: 4 - Beta
Classifier: Intended Audience :: Developers
Classifier: License :: OSI Approved :: MIT License
Classifier: Programming Language :: Python :: 3
Classifier: Programming Language :: Python :: 3.8
Classifier: Programming Language :: Python :: 3.9
Classifier: Programming Language :: Python :: 3.10
Classifier: Programming Language :: Python :: 3.11
Classifier: Programming Language :: Python :: 3.12
Classifier: Topic :: Software Development :: Libraries :: Python Modules
Classifier: Topic :: Software Development :: Version Control
Requires-Python: >=3.8
License-File: LICENSE
Requires-Dist: fastmcp>=2.0.0
Requires-Dist: requests>=2.31.0
Provides-Extra: dev
Requires-Dist: python-dotenv>=1.0.0; extra == "dev"
Requires-Dist: pytest>=7.0.0; extra == "dev"
Requires-Dist: black>=23.0.0; extra == "dev"
Requires-Dist: flake8>=6.0.0; extra == "dev"
Requires-Dist: mypy>=1.0.0; extra == "dev"
Dynamic: license-file
